{"Exaggerate": "The claim of Kroger stores charging a \"BLM charge\" is an exaggeration as the image of the receipt was altered and the original receipt showed a \"change shortage\" instead.", "Lack enough support": "The claim lacks enough support as the only evidence provided is an altered image of a receipt, which does not accurately represent the situation.", "Problematic assumption": "The claim assumes that the \"BLM charge\" is a deliberate fee imposed by Kroger stores, without considering alternative explanations or evidence.", "Contradict fact": "The claim contradicts the fact that the image of the receipt was altered and the original receipt did not show a \"BLM charge.\"", "Falters at times": "The claim falters at times by not providing accurate information and relying on misleading evidence.", "Exist alternative explanation": "The alternative explanation provided by Kroger is that the \"BLM charge\" is actually a result of the coin shortage in the United States, and Kroger has introduced alternatives for giving change to customers."}