{"Exaggerate": "The claim exaggerates by stating that a worker at a British dairy contaminated the company's products with HIV-infected blood.", "Lack enough support": "The claim lacks enough support as there is no evidence or credible sources provided to substantiate the claim.", "Problematic assumption": "The claim assumes that the rumor is true without any factual basis or evidence.", "Contradict fact": "The claim contradicts the fact that the rumor is false, as confirmed by the representative of the company.", "Understate": "There is no evidence of understatement bias in the claim.", "Falters at times": "There is no evidence of the claim faltering at times.", "Exist alternative explanation": "The claim does not provide any alternative explanation."}