{"Contradict fact": "The claim does not provide any specific facts to contradict.", "Exaggerate": "The claim exaggerates the actions of the ACLU by stating that they are seeking to have all cross-shaped headstones removed from federal cemeteries, without providing evidence or specific examples.", "Understate": "There is no evidence of understatement in the claim.", "Falters at times": "The claim does not falter at times.", "Lack enough support": "The claim lacks sufficient support or evidence to substantiate the ACLU's alleged actions.", "Problematic assumption": "The claim assumes that the ACLU is seeking to have cross-shaped headstones removed from federal cemeteries, without providing evidence to support this assumption.", "Exist alternative explanation": "The claim does not provide any alternative explanations or perspectives."}