{"Contradict fact": "None of the provided information contradicts any established facts.", "Exaggerate": "There is no exaggeration in the claim.", "Understate": "There is no understatement in the claim.", "Falters at times": "The claim does not falter at any point.", "Lack enough support": "The claim is supported by the information provided about the two separate news accounts reporting the death of the same person.", "Problematic assumption": "The claim does not contain any problematic assumptions.", "Exist alternative explanation": "There are no alternative explanations provided in the claim."}