{"Understate": "The expert's verdict does not indicate any understatements in the provided claim.", "Lack enough support": "The expert's verdict does not mention any lack of support in the provided claim.", "Problematic assumption": "The expert's verdict does not highlight any problematic assumptions in the provided claim.", "Exist alternative explanation": "The expert's verdict does not suggest any alternative explanations for the provided claim.", "Contradict fact": "The expert's verdict supports the claim and does not contradict any facts.", "Exaggerate": "The expert's verdict does not indicate any exaggerations in the provided claim.", "Falters at times": "The expert's verdict does not mention any instances where the claim falters."}