{"Lack enough support": "The claim lacks enough support as it is based on a fake Twitter account and the information provided is not verifiable.", "Problematic assumption": "The claim assumes that the loan between Eskom and Exim Bank of China is true, without providing any concrete evidence.", "Contradict fact": "The claim contradicts the fact that the Twitter account is fake and not associated with the Exim Bank of China.", "Exaggerate": "The claim may exaggerate the loan amount and repayment terms without providing reliable sources or evidence.", "Understate": "There is no evidence of understatement bias in the claim.", "Falters at times": "The claim falters at times as it relies on information from a fake Twitter account and does not provide enough evidence to support its validity.", "Exist alternative explanation": "There could be alternative explanations for the claim, such as misinformation or intentional spreading of fake news."}