{"Lack enough support": "The claim lacks evidence or proof to support the statement that Alexandria Ocasio-Cortez made the quoted statement.", "Contradict fact": "The claim contradicts the fact that there is no evidence of Alexandria Ocasio-Cortez making the statement.", "Exaggerate": "The claim exaggerates by attributing a false quote to Alexandria Ocasio-Cortez.", "Problematic assumption": "The claim assumes that Alexandria Ocasio-Cortez made the statement without any basis or evidence.", "Exist alternative explanation": "The claim does not consider alternative explanations for the origin of the false quote, such as it being a fabrication or satire."}