{"Problematic assumption": "The claim assumes that changing the word \"picnic\" to alternative terms like \"family outing, cookout, barbecue\" would solve any racial insensitivity.", "Lack enough support": "The claim lacks sufficient evidence or support to prove that the word \"picnic\" is racially insensitive.", "Exist alternative explanation": "Historians and experts have provided alternative explanations for the word \"picnic,\" suggesting that it does not have racist origins.", "Contradict fact": "The claim contradicts the fact that the word \"picnic\" has French roots and refers to a social gathering where people eat.", "Falters at times": "The claim falters by relying on anecdotal evidence and personal beliefs rather than concrete facts or research.", "Exaggerate": "The claim may exaggerate the racial insensitivity of the word \"picnic\" by attributing it to hangings of African Americans without sufficient evidence.", "Understate": "The claim may understate the historical context and complexity of lynchings by simplifying them to mere \"family outings\" or social gatherings."}