{"Exaggerate": "The claim exaggerates the effectiveness of budesonide as a cure for COVID-19.", "Lack enough support": "The claim lacks sufficient scientific evidence to support the assertion that budesonide can cure COVID-19.", "Problematic assumption": "The claim assumes that using budesonide as a treatment for COVID-19 would eliminate the need for other protective measures such as masks and social distancing, which is a problematic assumption.", "Contradict fact": "The claim contradicts the statement by health officials and medical experts who state that budesonide is not a cure for COVID-19.", "Understate": "N/A", "Falters at times": "N/A", "Exist alternative explanation": "N/A"}