{"Exaggerate": "The claim that Nigeria owes China 3 trillion naira is exaggerated, as the actual debt is much lower at $3.1 billion.", "Lack enough support": "The claim lacks enough support as it is based on an analysis piece that makes misleading or false assertions.", "Contradict fact": "The claim contradicts the fact that Nigeria's Chinese debt is actually $3.1 billion, not 3 trillion naira.", "Problematic assumption": "The claim assumes that Nigeria owes China a specific amount without providing sufficient evidence.", "Understate": "The claim may understate the actual debt by presenting a significantly lower figure than the real amount owed.", "Exist alternative explanation": "The claim does not provide alternative explanations for the increase in Nigeria's Chinese debt or the controversy surrounding it.", "Falters at times": "The claim falters at times by presenting inaccurate or misleading information about the debt owed to China."}