{"Contradict fact": "The claim contradicts the fact that Donald Trump never made the statement mentioned.", "Exaggerate": "The claim exaggerates by attributing a false statement to Donald Trump.", "Lack enough support": "The claim lacks enough support as it is based on a fake news article from a satire website.", "Problematic assumption": "The claim assumes that Donald Trump made a racist statement without any evidence.", "Exist alternative explanation": "An alternative explanation is that the claim is entirely fabricated and false."}