{"Lack enough support": "The claim lacks support as there is no evidence or announcement from the Trump family about donating $1 billion to the wall fund.", "Contradict fact": "The claim contradicts the fact that the Trump family has not made any announcement about the donation.", "Exaggerate": "The claim exaggerates the amount of the donation by stating it as $1 billion without any evidence.", "Problematic assumption": "The claim assumes that the Trump family has made a donation without any factual basis.", "Exist alternative explanation": "The alternative explanation is that the claim is a satirical story created by a publisher known for spreading hoaxes and fake news."}