{"Exaggerate": "The claim may be exaggerated as it states that the budget \"slashes investments in health care to pay for tax cuts to billionaires,\" implying a direct connection between the two.", "Understate": "There is no evidence of understatement in the claim.", "Falters at times": "The claim may falter at times as it does not provide enough evidence or details to support the connection between health care cuts and tax cuts for billionaires.", "Lack enough support": "The claim lacks enough support as it does not provide specific data or analysis to back up the assertion.", "Problematic assumption": "The claim assumes a direct link between health care cuts and tax cuts for billionaires without providing sufficient evidence.", "Exist alternative explanation": "The claim does not consider alternative explanations for the proposed budget cuts in health care."}