{"Lack enough support": "The claim lacks enough support as it is based on a doctored image and misleading posts on social media.", "Contradict fact": "The claim contradicts the fact that the image is not a genuine photo but a doctored image.", "Exaggerate": "The claim exaggerates the situation by stating that people fled in terror, while there is no evidence to support this.", "Problematic assumption": "The claim assumes that the human-shaped figure in the image is a genuine phenomenon, without considering alternative explanations.", "Exist alternative explanation": "The alternative explanation is that the image is a doctored photo of a kite designed by a UK-based artist.", "Falters at times": "The claim falters at times by presenting misleading information and false claims about the origin and authenticity of the image.", "Understate": "There is no evidence of understating bias in the provided claim."}