{"Exaggerate": "The claim falsely attributes a quote to Ruth Bader Ginsburg that she never made, thus exaggerating her views on pedophilia.", "Lack enough support": "The claim is not supported by any credible evidence or source, as it is based on a misinterpretation of a 1974 report.", "Contradict fact": "The claim contradicts the fact that Ruth Bader Ginsburg did not make the statement attributed to her.", "Problematic assumption": "The claim assumes that Ruth Bader Ginsburg supports pedophilia, which is a problematic and unfounded assumption.", "Exist alternative explanation": "The alternative explanation is that the claim is a misinterpretation and distortion of a report that Ginsburg co-authored, which focused on gendered language in the law, not pedophilia."}