{"Lack enough support": "The claim lacks evidence or support to prove its veracity.", "Problematic assumption": "The claim assumes that Melania Trump made a threat towards former President Barack Obama based on a fabricated quote.", "Contradict fact": "The claim contradicts the fact that Melania Trump did not issue a threat to Obama over the safety of her son.", "Exaggerate": "The claim exaggerates the situation by falsely attributing a threatening statement to Melania Trump.", "Falters at times": "The claim falters by relying on a fake news website, Yournewswire.com, which is known for spreading misinformation.", "Exist alternative explanation": "The claim fails to consider alternative explanations for the threat against Barron Trump, such as the actions of an ISIS supporter on Telegram."}