{"Exaggerate": "The claim exaggerates by stating that Tony Evers will raise property taxes, income taxes, and gas taxes by as much as a dollar a gallon.", "Understate": "The claim understates the actual positions of Tony Evers by not providing enough support or context for his tax plans.", "Lack enough support": "The claim lacks enough support to back up the assertion that Tony Evers will raise taxes to the extent mentioned.", "Problematic assumption": "The claim makes a problematic assumption that Tony Evers will raise all the taxes mentioned without considering alternative explanations or possibilities.", "Exist alternative explanation": "There may be alternative explanations for Tony Evers' tax plans that are not fully explored or considered in the claim."}