{"Lack enough support": "The claim lacks enough support as it does not provide specific evidence or sources to back up the statement.", "Problematic assumption": "The claim assumes that the Reagan Foundation's request to stop using Reagan's likeness on a fundraiser coin is a biased action.", "Exist alternative explanation": "The claim does not consider alternative explanations for the Reagan Foundation's request, such as copyright infringement concerns or a desire to maintain the integrity of Reagan's image.", "Contradict fact": "There is no contradiction of fact identified in the claim.", "Exaggerate": "There is no exaggeration identified in the claim.", "Understate": "There is no understatement identified in the claim.", "Falters at times": "There is no indication that the claim falters at times."}