{"Exaggerate": "The claim \"This [6.3%] growth is the highest to have been recorded for the past 8 years\" may be an exaggeration if there have been higher growth rates in the past 8 years that are not mentioned.", "Understate": "None of the provided claims appear to understate any information.", "Lack enough support": "The claim \"The public sector wage bill continues to rise\" lacks enough support as no data or evidence is provided to back up this statement.", "Problematic assumption": "None of the provided claims seem to be based on problematic assumptions.", "Exist alternative explanation": "None of the provided claims present alternative explanations for the stated information.", "Contradict fact": "None of the provided claims contradict any known facts.", "Falters at times": "None of the provided claims appear to falter at times."}