{"Exaggerate": "The claim exaggerates the effectiveness of hydroxychloroquine in preventing COVID-19 in people with lupus.", "Contradict fact": "The claim contradicts the fact that some people with lupus have indeed developed COVID-19.", "Lack enough support": "The claim lacks sufficient evidence or support to prove its assertion.", "Problematic assumption": "The claim assumes that people with lupus are not affected by the virus based on a study, without providing any details or supporting evidence for the study.", "Understate": "The claim understates the potential risks and need for caution for people with lupus in relation to COVID-19."}