{"Exaggerate": "The claim exaggerates the recognition of Aung San Suu Kyi as the \"mother of the world\" by stating that 43 countries have recognized her with this title, which is not true.", "Lack enough support": "The claim lacks sufficient evidence or credible sources to support the assertion that Aung San Suu Kyi has been recognized by 43 countries as the \"mother of the world.\"", "Contradict fact": "The claim contradicts the fact that there is no international award or recognition for Aung San Suu Kyi as the \"mother of the world.\"", "Problematic assumption": "The claim assumes that the images of a coin with the title \"Mother of peace. Aung San Suu Kyi\" are evidence of the recognition, but it is actually an artwork created by a Burmese artist.", "Understate": "None evident.", "Falters at times": "None evident.", "Exist alternative explanation": "The alternative explanation is that the images and claim are based on an artwork created by a Burmese artist, rather than actual recognition from 43 countries."}