{"Exaggerate": "The claim exaggerates the luxuriousness of the menu and implies that Sanders flew on a private jet.", "Understate": "The claim understates the fact that the menu was not different from Delta's regular offerings and that Sanders did not demand extravagant items.", "Lack enough support": "The claim lacks enough support to prove that Sanders flew on a private jet and that the menu was lavish.", "Problematic assumption": "The claim assumes that the menu and the mode of transportation reflect Sanders' personal beliefs and actions.", "Exist alternative explanation": "The claim does not consider the alternative explanation that the menu was standard for Delta's charter flights and not specifically requested by Sanders or his staff."}