{"Lack enough support": "The claim lacks sufficient evidence or proof to confirm the authenticity of the photograph.", "Problematic assumption": "The claim assumes that the photograph is genuine without verifying its authenticity.", "Exist alternative explanation": "There is a possibility that the photograph could be staged or manipulated, suggesting an alternative explanation for the image.", "Falters at times": "The claim's credibility is questioned due to the lack of confirmation from the photographer and the media's inability to reach him.", "Understate": "The claim does not downplay or understate any information or aspect.", "Exaggerate": "The claim does not exaggerate any information or aspect.", "Contradict fact": "The claim does not contradict any known facts."}