{"Exaggerate": "The claim does not appear to exaggerate any information. It simply asks if Indonesia has announced a ban on some online video games.", "Understate": "The claim does not understate any information. It accurately states the question being asked.", "Falters at times": "The claim does not falter at any point. It is a straightforward question.", "Lack enough support": "The claim is supported by the expert's verdict, which provides information about the announcement and the denial by the Indonesian Ministry of Communication.", "Problematic assumption": "The claim does not make any assumptions. It only asks if Indonesia has announced a ban on some online video games.", "Exist alternative explanation": "The claim does not provide any alternative explanations. It simply asks for information about the announcement."}